[
	{
		"key": "sb",
		"value": "E8ozYdR2EZF_KPg1A5zKD4kA",
		"domain": "facebook.com",
		"path": "/",
		"hostOnly": false,
		"creation": "2021-09-13T15:08:35.420Z",
		"lastAccessed": "2021-09-13T15:08:40.071Z"
	},
	{
		"key": "wd",
		"value": "1264x599",
		"domain": "facebook.com",
		"path": "/",
		"hostOnly": false,
		"creation": "2021-09-13T15:08:35.746Z",
		"lastAccessed": "2021-09-13T15:08:40.071Z"
	},
	{
		"key": "c_user",
		"value": "100064427343444",
		"domain": "facebook.com",
		"path": "/",
		"hostOnly": false,
		"creation": "2021-09-13T15:08:35.855Z",
		"lastAccessed": "2021-09-13T15:08:40.071Z"
	},
	{
		"key": "spin",
		"value": "r.1004383506_b.trunk_t.1631519339_s.1_v.2_",
		"domain": "facebook.com",
		"path": "/",
		"hostOnly": false,
		"creation": "2021-09-13T15:08:35.856Z",
		"lastAccessed": "2021-09-13T15:08:40.071Z"
	},
	{
		"key": "datr",
		"value": "ZwI_YRKgypkpIzIoStxNCb-B",
		"domain": "facebook.com",
		"path": "/",
		"hostOnly": false,
		"creation": "2021-09-13T15:08:35.857Z",
		"lastAccessed": "2021-09-13T15:08:40.071Z"
	},
	{
		"key": "xs",
		"value": "20%3AOTO87yLJ8MqejQ%3A2%3A1631519334%3A-1%3A6378%3A%3AAcWurptSHsihAkWVncBz2xX7StnfBCrGLLDgMpTk9g",
		"domain": "facebook.com",
		"path": "/",
		"hostOnly": false,
		"creation": "2021-09-13T15:08:35.858Z",
		"lastAccessed": "2021-09-13T15:08:40.071Z"
	},
	{
		"key": "fr",
		"value": "1nvS48eia7Uy6JaTX.AWVf2MSCfk0a-f7BPB3asDdxWz4.BhPwJt.iM.AAA.0.0.BhPwJt.AWVCSCWNRFg",
		"domain": "facebook.com",
		"path": "/",
		"hostOnly": false,
		"creation": "2021-09-13T15:08:35.859Z",
		"lastAccessed": "2021-09-13T15:08:40.071Z"
	},
	{
		"key": "presence",
		"value": "C%7B%22t3%22%3A%5B%7B%22i%22%3A%22g.4298048533581708%22%7D%2C%7B%22i%22%3A%22g.5995586437148654%22%7D%5D%2C%22utc3%22%3A1631519376807%2C%22v%22%3A1%7D",
		"domain": "facebook.com",
		"path": "/",
		"hostOnly": false,
		"creation": "2021-09-13T15:08:35.860Z",
		"lastAccessed": "2021-09-13T15:08:40.071Z"
	},
	{
		"key": "sb",
		"value": "E8ozYdR2EZF_KPg1A5zKD4kA",
		"domain": "facebook.com",
		"path": "/",
		"hostOnly": false,
		"creation": "2021-09-13T15:08:35.420Z",
		"lastAccessed": "2021-09-13T15:08:40.071Z"
	},
	{
		"key": "wd",
		"value": "1264x599",
		"domain": "facebook.com",
		"path": "/",
		"hostOnly": false,
		"creation": "2021-09-13T15:08:35.746Z",
		"lastAccessed": "2021-09-13T15:08:40.071Z"
	},
	{
		"key": "c_user",
		"value": "100064427343444",
		"domain": "facebook.com",
		"path": "/",
		"hostOnly": false,
		"creation": "2021-09-13T15:08:35.855Z",
		"lastAccessed": "2021-09-13T15:08:40.071Z"
	},
	{
		"key": "spin",
		"value": "r.1004383506_b.trunk_t.1631519339_s.1_v.2_",
		"domain": "facebook.com",
		"path": "/",
		"hostOnly": false,
		"creation": "2021-09-13T15:08:35.856Z",
		"lastAccessed": "2021-09-13T15:08:40.071Z"
	},
	{
		"key": "datr",
		"value": "ZwI_YRKgypkpIzIoStxNCb-B",
		"domain": "facebook.com",
		"path": "/",
		"hostOnly": false,
		"creation": "2021-09-13T15:08:35.857Z",
		"lastAccessed": "2021-09-13T15:08:40.071Z"
	},
	{
		"key": "xs",
		"value": "20%3AOTO87yLJ8MqejQ%3A2%3A1631519334%3A-1%3A6378%3A%3AAcWurptSHsihAkWVncBz2xX7StnfBCrGLLDgMpTk9g",
		"domain": "facebook.com",
		"path": "/",
		"hostOnly": false,
		"creation": "2021-09-13T15:08:35.858Z",
		"lastAccessed": "2021-09-13T15:08:40.071Z"
	},
	{
		"key": "fr",
		"value": "1nvS48eia7Uy6JaTX.AWVf2MSCfk0a-f7BPB3asDdxWz4.BhPwJt.iM.AAA.0.0.BhPwJt.AWVCSCWNRFg",
		"domain": "facebook.com",
		"path": "/",
		"hostOnly": false,
		"creation": "2021-09-13T15:08:35.859Z",
		"lastAccessed": "2021-09-13T15:08:40.071Z"
	},
	{
		"key": "presence",
		"value": "C%7B%22t3%22%3A%5B%7B%22i%22%3A%22g.4298048533581708%22%7D%2C%7B%22i%22%3A%22g.5995586437148654%22%7D%5D%2C%22utc3%22%3A1631519376807%2C%22v%22%3A1%7D",
		"domain": "facebook.com",
		"path": "/",
		"hostOnly": false,
		"creation": "2021-09-13T15:08:35.860Z",
		"lastAccessed": "2021-09-13T15:08:40.071Z"
	}
]